README.md
setup.py
knowledge_neurons/__init__.py
knowledge_neurons/data.py
knowledge_neurons/knowledge_neurons.py
knowledge_neurons/patch.py
knowledge_neurons/tests.py
knowledge_neurons.egg-info/PKG-INFO
knowledge_neurons.egg-info/SOURCES.txt
knowledge_neurons.egg-info/dependency_links.txt
knowledge_neurons.egg-info/requires.txt
knowledge_neurons.egg-info/top_level.txt