Metadata-Version: 2.1
Name: knowledge-neurons
Version: 0.0.2
Summary: A library for finding knowledge neurons in pretrained transformer models
Home-page: https://github.com/EleutherAI/knowledge-neurons
Author: Sid Black
Author-email: sdtblck@gmail.com
License: MIT
Platform: UNKNOWN
Classifier: License :: OSI Approved :: MIT License
Classifier: Programming Language :: Python :: 3.6
Classifier: Programming Language :: Python :: 3.7
Classifier: Programming Language :: Python :: 3.8
Classifier: Programming Language :: Python :: 3.9
Classifier: Programming Language :: Python :: 3.10
